predicate_dispatch.py
py.typed
predicate_dispatch-0.4.0.dist-info/WHEEL
predicate_dispatch-0.4.0.dist-info/METADATA
predicate_dispatch-0.4.0.dist-info/licenses/LICENSE.txt
predicate_dispatch-0.4.0.dist-info/RECORD
