Metadata-Version: 2.1
Name: predicate_dispatch
Version: 0.4.0
Summary: Predicative dispatch decorator for Python, based on idea from book "Functional Programming in Python".
License: Apache-2.0
Keywords: dispatch,functional programming
Author-email: Dmitriy Pertsev <davaeron@gmail.com>
Requires-Python: >=3.7
Classifier: Intended Audience :: Developers
Classifier: License :: OSI Approved :: Apache Software License
Classifier: Operating System :: OS Independent
Classifier: Programming Language :: Python :: 3
Classifier: Programming Language :: Python :: 3.10
Classifier: Programming Language :: Python :: 3.11
Classifier: Programming Language :: Python :: 3.7
Classifier: Programming Language :: Python :: 3.8
Classifier: Programming Language :: Python :: 3.9
Classifier: Topic :: Software Development :: Libraries
Classifier: Typing :: Typed
Project-URL: Bug Tracker, https://github.com/pertsevds/predicate_dispatch/issues
Project-URL: Documentation, https://github.com/pertsevds/predicate_dispatch
Project-URL: Homepage, https://github.com/pertsevds/predicate_dispatch
Project-URL: Repository, https://github.com/pertsevds/predicate_dispatch
